wheel_axle/runtime/__init__.py
wheel_axle/runtime/_axle.py
wheel_axle/runtime/_common.py
wheel_axle/runtime/_libpython.py
wheel_axle/runtime/_symlinks.py
wheel_axle/runtime/_wheel.py
wheel_axle/runtime/constants.py
wheel_axle_runtime-0.0.10.dist-info/METADATA
wheel_axle_runtime-0.0.10.dist-info/WHEEL
wheel_axle_runtime-0.0.10.dist-info/namespace_packages.txt
wheel_axle_runtime-0.0.10.dist-info/top_level.txt
wheel_axle_runtime-0.0.10.dist-info/zip-safe
wheel_axle_runtime-0.0.10.dist-info/RECORD
