Metadata-Version: 2.4
Name: wheel-axle-runtime
Version: 0.0.10
Summary: Axle Runtime is the runtime part of the Python Wheel enhancement library
Home-page: https://github.com/karellen/wheel-axle-runtime
Author: Karellen, Inc.
Author-email: supervisor@karellen.co
Maintainer: Arcadiy Ivanov
Maintainer-email: arcadiy@karellen.co
License: Apache-2.0
Project-URL: Bug Tracker, https://github.com/karellen/wheel-axle-runtime/issues
Project-URL: Documentation, https://github.com/karellen/wheel-axle-runtime/
Project-URL: Source Code, https://github.com/karellen/wheel-axle-runtime/
Keywords: wheel packaging setuptools bdist_wheel symlink postinstall
Classifier: Programming Language :: Python :: 3.9
Classifier: Programming Language :: Python :: 3.10
Classifier: Programming Language :: Python :: 3.11
Classifier: Programming Language :: Python :: 3.12
Classifier: Programming Language :: Python :: 3.13
Classifier: Programming Language :: Python :: 3.14
Classifier: Operating System :: MacOS :: MacOS X
Classifier: Operating System :: POSIX
Classifier: Operating System :: POSIX :: Linux
Classifier: Topic :: System :: Archiving :: Packaging
Classifier: Topic :: Software Development :: Build Tools
Classifier: Intended Audience :: Developers
Classifier: Development Status :: 4 - Beta
Requires-Python: >=3.9
Requires-Dist: filelock
Requires-Dist: pip
Dynamic: author
Dynamic: author-email
Dynamic: classifier
Dynamic: description
Dynamic: description-content-type
Dynamic: home-page
Dynamic: keywords
Dynamic: license
Dynamic: maintainer
Dynamic: maintainer-email
Dynamic: project-url
Dynamic: requires-dist
Dynamic: requires-python
Dynamic: summary
